{
  "index": "Introduction",
  "machine_learning": "Machine Learning",
  "neural_networks": "Neural Networks",
  "natural_language_processing": "Natural Language Processing",
  "computer_vision": "Computer Vision",
  "ai_ethics_and_societal_implications": "AI Ethics and Societal Implications",
    "models": {
      "title": "Models",
      "type": "menu",
      "items": {
        "arboria": {
          "title": "Arboria",
          "href": "https://ai.yukiolabs.com/arboria",
          "newWindow": true
        },
        "proteus": {
          "title": "Proteus",
          "href": "https://ai.yukiolabs.com/proteus",
          "newWindow": true
        },
        "loresmith": {
          "title": "LoreSmith",
          "href": "https://ai.yukiolabs.com/loresmith",
          "newWindow": true
        }
      }
    },
  "latest": {
    "title": "News",
    "type": "page"
  },
  "research": {
    "title": "Research",
    "type": "page"
  },
  "about": {
    "title": "About",
    "type": "page"
  },
  "contact": {
    "title": "Contact ↗",
    "type": "page",
    "href": "https://chrisadams.io",
    "newWindow": true
  }
}
